helloworldgeez/__init__.py
helloworldgeez/cli.py
helloworldgeez/fun.py
helloworldgeez-0.3.1-py3.7.egg-info/PKG-INFO
helloworldgeez-0.3.1-py3.7.egg-info/SOURCES.txt
helloworldgeez-0.3.1-py3.7.egg-info/dependency_links.txt
helloworldgeez-0.3.1-py3.7.egg-info/entry_points.txt
helloworldgeez-0.3.1-py3.7.egg-info/top_level.txt
helloworldgeez-0.3.1.dist-info/DESCRIPTION.rst
helloworldgeez-0.3.1.dist-info/METADATA
helloworldgeez-0.3.1.dist-info/RECORD
helloworldgeez-0.3.1.dist-info/WHEEL
helloworldgeez-0.3.1.dist-info/entry_points.txt
helloworldgeez-0.3.1.dist-info/metadata.json
helloworldgeez-0.3.1.dist-info/top_level.txt
