Metadata-Version: 2.0
Name: helloworldgeez
Version: 0.3.1
Summary: test pypl
Home-page: UNKNOWN
Author: UNKNOWN
Author-email: UNKNOWN
License: UNKNOWN
Platform: UNKNOWN
